inclusivewriting/__init__.py
inclusivewriting/configuration.json
inclusivewriting/file_utils.py
inclusivewriting/locale_utils.py
inclusivewriting/main.py
inclusivewriting/suggestions.py
inclusivewriting/text_utils.py
inclusivewriting/unicode_utils.py
inclusivewriting/version.py
inclusivewriting/locales/inclusive.bot
inclusivewriting/locales/inclusivewriting.bot
inclusivewriting/locales/en/LC_MESSAGES/inclusive.mo
inclusivewriting/locales/en/LC_MESSAGES/inclusivewriting.mo
inclusivewriting/locales/en/LC_MESSAGES/inclusivewriting.po
inclusivewriting/locales/en_US/LC_MESSAGES/inclusive.mo
inclusivewriting/locales/en_US/LC_MESSAGES/inclusivewriting.mo
inclusivewriting/locales/en_US/LC_MESSAGES/inclusivewriting.po
inclusivewriting/locales/fr/LC_MESSAGES/inclusive.mo
inclusivewriting/locales/fr/LC_MESSAGES/inclusivewriting.mo
inclusivewriting/locales/fr/LC_MESSAGES/inclusivewriting.po
inclusivewriting/locales/fr_FR/LC_MESSAGES/inclusive.mo
inclusivewriting/locales/fr_FR/LC_MESSAGES/inclusivewriting.mo
inclusivewriting/locales/fr_FR/LC_MESSAGES/inclusivewriting.po
inclusivewriting/resources/__init__.py
inclusivewriting/resources/en/list.json
inclusivewriting/resources/en/pronouns.json
tests/__init__.py
tests/file_utils_test.py
tests/locale_utils_test.py
tests/suggestions_test.py
tests/tests.py
tests/unicode_utils_test.py
inclusivewriting-0.8.dist-info/LICENSE
inclusivewriting-0.8.dist-info/METADATA
inclusivewriting-0.8.dist-info/WHEEL
inclusivewriting-0.8.dist-info/top_level.txt
inclusivewriting-0.8.dist-info/RECORD
