Metadata-Version: 2.1
Name: inclusivewriting
Version: 0.8
Summary: Python multilingual application for inclusive writing
Home-page: https://github.com/johnsamuelwrites/inclusive
Author: John Samuel
Author-email: johnsamuelwrites@example.com
License: UNKNOWN
Platform: UNKNOWN
Classifier: Programming Language :: Python :: 3
Classifier: License :: OSI Approved :: GNU General Public License v3 or later (GPLv3+)
Classifier: Operating System :: OS Independent
Requires-Python: >=3.7
License-File: LICENSE
Requires-Dist: rich (>=10.9.0)
Requires-Dist: typer (>=0.3.2)
Requires-Dist: babel (>=2.9.1)
